eln/__init__.py
eln/app.py
eln/commands/__init__.py
eln/commands/cli.py
eln/commands/_ipsum/__init__.py
eln/commands/_ipsum/main.py
eln/commands/azuracast/__init__.py
eln/commands/azuracast/client.py
eln/commands/azuracast/main.py
eln/commands/azuracast/templates/__init__.py
eln/commands/azuracast/templates/notification.py
eln/commands/azuracast/templates/print_std.py
eln/commands/azuracast/templates/slack.py
eln/commands/convert/__init__.py
eln/commands/convert/main.py
eln/commands/digitalocean/__init__.py
eln/commands/digitalocean/main.py
eln/commands/news/__init__.py
eln/commands/news/client.py
eln/commands/news/main.py
eln/commands/news/templates/__init__.py
eln/commands/news/templates/articles.py
eln/commands/news/templates/sources.py
eln/commands/plot/__init__.py
eln/commands/plot/main.py
eln/commands/plot/readers/__init__.py
eln/commands/stub/__init__.py
eln/commands/stub/main.py
eln/commands/stub/bottle/__init__.py
eln/commands/stub/bottle/main.py
eln/commands/stub/bottle/templates/__init__.py
eln/commands/stub/bottle/templates/app.tpl
eln/commands/stub/bottle/templates/dbconfig.tpl
eln/commands/stub/bottle/templates/gitignore.tpl
eln/commands/stub/bottle/templates/pipfile.tpl
eln/commands/stub/cpp/__init__.py
eln/commands/stub/cpp/main.py
eln/commands/stub/cpp/templates/__init__.py
eln/commands/stub/cpp/templates/class.tpl
eln/commands/stub/cpp/templates/gitignore.tpl
eln/commands/stub/cpp/templates/header.tpl
eln/commands/stub/cpp/templates/main.tpl
eln/commands/stub/cpp/templates/main_test.tpl
eln/commands/stub/helpers/__init__.py
eln/commands/stub/helpers/creator.py
eln/commands/stub/package/__init__.py
eln/commands/stub/package/main.py
eln/commands/stub/package/templates/__init__.py
eln/commands/stub/package/templates/app.tpl
eln/commands/stub/package/templates/gitignore.tpl
eln/commands/stub/package/templates/license.tpl
eln/commands/stub/package/templates/manifest.tpl
eln/commands/stub/package/templates/pipfile.tpl
eln-0.0.0b10.dist-info/LICENSE.txt
eln-0.0.0b10.dist-info/METADATA
eln-0.0.0b10.dist-info/WHEEL
eln-0.0.0b10.dist-info/entry_points.txt
eln-0.0.0b10.dist-info/top_level.txt
eln-0.0.0b10.dist-info/RECORD
