Metadata-Version: 2.1
Name: eln
Version: 0.0.0b10
Summary: A command-line tool for quick access to web services
Home-page: https://github.com/lehvitus/eln
Author: Leo Neto
Author-email: projects@lehvitus.com
License: BSD
Project-URL: Documentation, https://github.com/lehvitus/eln/
Project-URL: Source Code, https://github.com/lehvitus/eln/
Keywords: cli command line tools miscellaneous news forecast weather digitalocean s3 aws uploads
Platform: any
Classifier: Development Status :: 4 - Beta
Classifier: Intended Audience :: Developers
Classifier: License :: OSI Approved :: BSD License
Classifier: Natural Language :: English
Classifier: Environment :: MacOS X
Classifier: Operating System :: MacOS
Classifier: Programming Language :: Python
Classifier: Programming Language :: Python :: 3
Classifier: Programming Language :: Python :: 3.6
Classifier: Programming Language :: Python :: 3.7
Classifier: Programming Language :: Python :: 3 :: Only
Classifier: Topic :: Software Development :: Libraries :: Application Frameworks
Classifier: Topic :: Software Development :: Libraries :: Python Modules
Requires-Dist: Click (==7.0)
Requires-Dist: requests (==2.22.0)
Requires-Dist: jinja2 (==2.10.3)
Requires-Dist: pandas
Requires-Dist: matplotlib
Requires-Dist: inflection (==0.3.1)
Requires-Dist: python-digitalocean (==1.14.0)
Requires-Dist: python-dotenv (==0.10.3)
Requires-Dist: pytest
Requires-Dist: tox
Requires-Dist: pyttsx3 (==2.71) ; platform_system == "MacOS"
